synbio_promoter/__init__.py
synbio_promoter/cli.py
synbio_promoter/predictor.py
synbio_promoter_predictor-0.1.3.dist-info/licenses/LICENSE
synbio_promoter_predictor-0.1.3.dist-info/METADATA
synbio_promoter_predictor-0.1.3.dist-info/WHEEL
synbio_promoter_predictor-0.1.3.dist-info/entry_points.txt
synbio_promoter_predictor-0.1.3.dist-info/top_level.txt
synbio_promoter_predictor-0.1.3.dist-info/RECORD
